simple_project/__init__.py
simple_project-1.2.3.dist-info/WHEEL
simple_project-1.2.3.dist-info/METADATA
simple_project-1.2.3.dist-info/RECORD
