Metadata-Version: 2.1
Name: simple-project
Version: 1.2.3
Summary: Some description.
Home-page: https://poetry.eustace.io
License: MIT
Keywords: packaging,dependency,poetry
Author: Sébastien Eustace
Author-email: sebastien@eustace.io
Requires-Python: >=2.7, !=3.0.*, !=3.1.*, !=3.2.*, !=3.3.*, !=3.4.*, !=3.5.*
Classifier: License :: OSI Approved :: MIT License
Classifier: Programming Language :: Python :: 2
Classifier: Programming Language :: Python :: 2.7
Classifier: Programming Language :: Python :: 3
Classifier: Programming Language :: Python :: 3.6
Classifier: Programming Language :: Python :: 3.7
Classifier: Topic :: Software Development :: Build Tools
Classifier: Topic :: Software Development :: Libraries :: Python Modules
Project-URL: Documentation, https://poetry.eustace.io/docs
Project-URL: Repository, https://github.com/sdispater/poetry
